{
    "Name":  "AdventureWorks2014",
    "Tables":  [
                   {
                       "Name":  "Employee",
                       "Schema":  "HumanResources",
                       "Columns":  [
                                       {
                                           "Name":  "NationalIDNumber",
                                           "ColumnType":  "nvarchar",
                                           "CharacterString":  null,
                                           "MinValue":  8,
                                           "MaxValue":  15,
                                           "MaskingType":  "Random",
                                           "SubType":  "String2",
                                           "Format":  null,
                                           "Deterministic":  false,
                                           "Nullable":  false,
                                           "Composite":  null
                                       },
                                       {
                                           "Name":  "LoginID",
                                           "ColumnType":  "nvarchar",
                                           "CharacterString":  null,
                                           "MinValue":  null,
                                           "MaxValue":  15,
                                           "MaskingType":  "Internet",
                                           "SubType":  "UserName",
                                           "Format":  null,
                                           "Deterministic":  false,
                                           "Nullable":  false,
                                           "Composite":  null
                                       },
                                       {
                                           "Name":  "BirthDate",
                                           "ColumnType":  "date",
                                           "CharacterString":  null,
                                           "MinValue":  "1/1/1970",
                                           "MaxValue":  "1/1/1980",
                                           "MaskingType":  "Date",
                                           "SubType":  "Past",
                                           "Format":  null,
                                           "Deterministic":  false,
                                           "Nullable":  false,
                                           "Composite":  null
                                       },
                                       {
                                           "Name":  "MaritalStatus",
                                           "ColumnType":  "nchar",
                                           "CharacterString":  "SM",
                                           "MinValue":  0,
                                           "MaxValue":  1,
                                           "MaskingType":  "Random",
                                           "SubType":  "String2",
                                           "Format":  null,
                                           "Deterministic":  false,
                                           "Nullable":  false,
                                           "Composite":  null
                                       },
                                       {
                                           "Name":  "Gender",
                                           "ColumnType":  "nchar",
                                           "CharacterString":  "MF",
                                           "MinValue":  0,
                                           "MaxValue":  1,
                                           "MaskingType":  "Random",
                                           "SubType":  "String2",
                                           "Format":  null,
                                           "Deterministic":  false,
                                           "Nullable":  false,
                                           "Composite":  null
                                       },
                                       {
                                           "Name":  "HireDate",
                                           "ColumnType":  "date",
                                           "CharacterString":  null,
                                           "MinValue":  null,
                                           "MaxValue":  null,
                                           "MaskingType":  "Date",
                                           "SubType":  "Past",
                                           "Format":  null,
                                           "Deterministic":  false,
                                           "Nullable":  false,
                                           "Composite":  null
                                       },
                                       {
                                           "Name":  "rowguid",
                                           "ColumnType":  "uniqueidentifier",
                                           "CharacterString":  null,
                                           "MinValue":  null,
                                           "MaxValue":  null,
                                           "MaskingType":  "Random",
                                           "SubType":  "Guid",
                                           "Format":  null,
                                           "Deterministic":  false,
                                           "Nullable":  false,
                                           "Composite":  null
                                       }
                                   ],
                       "HasUniqueIndex":  true
                   },
                   {
                       "Name":  "EmployeeDepartmentHistory",
                       "Schema":  "HumanResources",
                       "Columns":  [
                                       {
                                           "Name":  "StartDate",
                                           "ColumnType":  "date",
                                           "CharacterString":  null,
                                           "MinValue":  null,
                                           "MaxValue":  null,
                                           "MaskingType":  "Date",
                                           "SubType":  "Past",
                                           "Format":  null,
                                           "Deterministic":  false,
                                           "Nullable":  false,
                                           "Composite":  null
                                       },
                                       {
                                           "Name":  "EndDate",
                                           "ColumnType":  "date",
                                           "CharacterString":  null,
                                           "MinValue":  null,
                                           "MaxValue":  null,
                                           "MaskingType":  "Date",
                                           "SubType":  "Past",
                                           "Format":  null,
                                           "Deterministic":  false,
                                           "Nullable":  true,
                                           "Composite":  null
                                       },
                                       {
                                           "Name":  "ModifiedDate",
                                           "ColumnType":  "datetime",
                                           "CharacterString":  null,
                                           "MinValue":  null,
                                           "MaxValue":  null,
                                           "MaskingType":  "Date",
                                           "SubType":  "Past",
                                           "Format":  null,
                                           "Deterministic":  false,
                                           "Nullable":  false,
                                           "Composite":  null
                                       }
                                   ],
                       "HasUniqueIndex":  true
                   },
                   {
                       "Name":  "EmployeePayHistory",
                       "Schema":  "HumanResources",
                       "Columns":  [
                                       {
                                           "Name":  "RateChangeDate",
                                           "ColumnType":  "datetime",
                                           "CharacterString":  null,
                                           "MinValue":  null,
                                           "MaxValue":  null,
                                           "MaskingType":  "Date",
                                           "SubType":  "Past",
                                           "Format":  null,
                                           "Deterministic":  false,
                                           "Nullable":  false,
                                           "Composite":  null
                                       },
                                       {
                                           "Name":  "Rate",
                                           "ColumnType":  "money",
                                           "CharacterString":  null,
                                           "MinValue":  -922337203685477.62,
                                           "MaxValue":  922337203685477.62,
                                           "MaskingType":  "Commerce",
                                           "SubType":  "Price",
                                           "Format":  null,
                                           "Deterministic":  false,
                                           "Nullable":  false,
                                           "Composite":  null
                                       },
                                       {
                                           "Name":  "ModifiedDate",
                                           "ColumnType":  "datetime",
                                           "CharacterString":  null,
                                           "MinValue":  null,
                                           "MaxValue":  null,
                                           "MaskingType":  "Date",
                                           "SubType":  "Past",
                                           "Format":  null,
                                           "Deterministic":  false,
                                           "Nullable":  false,
                                           "Composite":  null
                                       }
                                   ],
                       "HasUniqueIndex":  true
                   }
               ]
}
